string2date/__init__.py
string2date/string2date.py
string2date-0.0.3.dist-info/LICENSE
string2date-0.0.3.dist-info/METADATA
string2date-0.0.3.dist-info/WHEEL
string2date-0.0.3.dist-info/top_level.txt
string2date-0.0.3.dist-info/RECORD
