Metadata-Version: 2.1
Name: string2date
Version: 0.0.3
Summary: string to date
Home-page: https://github.com/BigDataFounder/string2date
Author: hurpe
Author-email: hurpe.ma@gmail.com
License: MIT
Platform: UNKNOWN
